{
  "timestamp": "2025-12-19T03:34:02.535Z",
  "date": "2025-12-19",
  "repositories": [
    {
      "org": "konveyor",
      "repo": "analyzer-lsp",
      "contributors": 11,
      "contributorsList": [
        "pranavgaikwad",
        "tsanders-rh",
        "dymurray",
        "shawn-hurley",
        "savitharaghunathan",
        "jmle",
        "aufi",
        "eemcmullan",
        "jmontleon",
        "ibolton336",
        "djzager"
      ],
      "newContributors": 8,
      "newContributorsList": [
        "pranavgaikwad",
        "tsanders-rh",
        "dymurray",
        "shawn-hurley",
        "savitharaghunathan",
        "jmle",
        "aufi",
        "eemcmullan"
      ],
      "avgIssueResponseMs": 180000,
      "avgPRResponseMs": 31236666.666666668,
      "prMergeRate": 71.11111111111111,
      "openIssues": 50,
      "openPRs": 7,
      "coverage": null,
      "snykVulnerabilities": null
    },
    {
      "org": "konveyor",
      "repo": "enhancements",
      "contributors": 7,
      "contributorsList": [
        "rromannissen",
        "djzager",
        "tsanders-rh",
        "jmle",
        "shawn-hurley",
        "dymurray",
        "fabianvf"
      ],
      "newContributors": 2,
      "newContributorsList": [
        "rromannissen",
        "djzager"
      ],
      "avgIssueResponseMs": 0,
      "avgPRResponseMs": 234084000,
      "prMergeRate": 100,
      "openIssues": 52,
      "openPRs": 6,
      "coverage": null,
      "snykVulnerabilities": null
    },
    {
      "org": "konveyor",
      "repo": "java-analyzer-bundle",
      "contributors": 6,
      "contributorsList": [
        "pranavgaikwad",
        "shawn-hurley",
        "cmoulliard",
        "jmontleon",
        "tsanders-rh",
        "jmle"
      ],
      "newContributors": 2,
      "newContributorsList": [
        "pranavgaikwad",
        "shawn-hurley"
      ],
      "avgIssueResponseMs": 0,
      "avgPRResponseMs": 1190626500,
      "prMergeRate": 57.14285714285714,
      "openIssues": 19,
      "openPRs": 1,
      "coverage": null,
      "snykVulnerabilities": null
    },
    {
      "org": "konveyor",
      "repo": "kai",
      "contributors": 7,
      "contributorsList": [
        "tsanders-rh",
        "pranavgaikwad",
        "savitharaghunathan",
        "shawn-hurley",
        "JonahSussman",
        "fabianvf",
        "dymurray"
      ],
      "newContributors": 2,
      "newContributorsList": [
        "tsanders-rh",
        "pranavgaikwad"
      ],
      "avgIssueResponseMs": 0,
      "avgPRResponseMs": 67747000,
      "prMergeRate": 60,
      "openIssues": 111,
      "openPRs": 19,
      "coverage": null,
      "snykVulnerabilities": {
        "critical": 0,
        "high": 4,
        "medium": 14,
        "low": 1,
        "total": 19
      }
    },
    {
      "org": "konveyor",
      "repo": "kantra",
      "contributors": 8,
      "contributorsList": [
        "pranavgaikwad",
        "eemcmullan",
        "tsanders-rh",
        "shawn-hurley",
        "dymurray",
        "gciavarrini",
        "JuanmaBM",
        "jmle"
      ],
      "newContributors": 5,
      "newContributorsList": [
        "pranavgaikwad",
        "eemcmullan",
        "tsanders-rh",
        "shawn-hurley",
        "dymurray"
      ],
      "avgIssueResponseMs": 0,
      "avgPRResponseMs": 42105000,
      "prMergeRate": 68,
      "openIssues": 37,
      "openPRs": 4,
      "coverage": 38,
      "snykVulnerabilities": null
    },
    {
      "org": "konveyor",
      "repo": "operator",
      "contributors": 8,
      "contributorsList": [
        "fabianvf",
        "shawn-hurley",
        "jortel",
        "jmontleon",
        "sjd78",
        "aufi",
        "tsanders-rh",
        "dymurray"
      ],
      "newContributors": 2,
      "newContributorsList": [
        "fabianvf",
        "shawn-hurley"
      ],
      "avgIssueResponseMs": 0,
      "avgPRResponseMs": 90000,
      "prMergeRate": 66.66666666666666,
      "openIssues": 11,
      "openPRs": 5,
      "coverage": null,
      "snykVulnerabilities": null
    },
    {
      "org": "konveyor",
      "repo": "rulesets",
      "contributors": 3,
      "contributorsList": [
        "tsanders-rh",
        "jmle",
        "dymurray"
      ],
      "newContributors": 2,
      "newContributorsList": [
        "tsanders-rh",
        "jmle"
      ],
      "avgIssueResponseMs": 0,
      "avgPRResponseMs": 103484000,
      "prMergeRate": 100,
      "openIssues": 110,
      "openPRs": 12,
      "coverage": null,
      "snykVulnerabilities": null
    },
    {
      "org": "konveyor",
      "repo": "tackle2-hub",
      "contributors": 5,
      "contributorsList": [
        "mguetta1",
        "jortel",
        "fabianvf",
        "tsanders-rh",
        "aufi"
      ],
      "newContributors": 3,
      "newContributorsList": [
        "mguetta1",
        "jortel",
        "fabianvf"
      ],
      "avgIssueResponseMs": 0,
      "avgPRResponseMs": 767007000,
      "prMergeRate": 88.23529411764706,
      "openIssues": 17,
      "openPRs": 7,
      "coverage": null,
      "snykVulnerabilities": null
    },
    {
      "org": "konveyor",
      "repo": "tackle2-ui",
      "contributors": 11,
      "contributorsList": [
        "ibragins",
        "sshveta",
        "sjd78",
        "nachandr",
        "mguetta1",
        "dependabot[bot]",
        "abrugaro",
        "msajidmansoori12",
        "fabianvf",
        "tsanders-rh",
        "aufi"
      ],
      "newContributors": 9,
      "newContributorsList": [
        "ibragins",
        "sshveta",
        "sjd78",
        "nachandr",
        "mguetta1",
        "dependabot[bot]",
        "abrugaro",
        "msajidmansoori12",
        "fabianvf"
      ],
      "avgIssueResponseMs": 0,
      "avgPRResponseMs": 8560500,
      "prMergeRate": 76.92307692307693,
      "openIssues": 59,
      "openPRs": 13,
      "coverage": 39,
      "snykVulnerabilities": null
    }
  ],
  "metrics": {
    "totalContributors": 26,
    "newContributors": 20,
    "avgResponseTime": 135920037.03703704,
    "avgIssueResponse": 180000,
    "avgPRResponse": 271660074.0740741,
    "prMergeRate": 76.45322288459543,
    "openIssues": 466,
    "openPRs": 74,
    "repositories": 9
  },
  "prMetrics": {
    "avgReviewTime": 271660074.0740741,
    "avgMergeTime": 2716600740.740741,
    "avgRevisions": 3
  },
  "issueMetrics": {
    "closureRate": 88,
    "avgTimeToClose": 3600000,
    "avgTimeToFirstResponse": 180000,
    "responseCoverage": 97,
    "communityResponseRate": 38
  },
  "maintainerMetrics": {
    "activeMaintainers": 9,
    "responseConcentration": 64
  },
  "activityHeatmap": [
    [
      15,
      3,
      5,
      13,
      7,
      18,
      16,
      16,
      6,
      19,
      17,
      11,
      17,
      12,
      11,
      10,
      17,
      18,
      15,
      3,
      14,
      17,
      17,
      2
    ],
    [
      6,
      12,
      8,
      14,
      16,
      17,
      18,
      8,
      18,
      9,
      11,
      2,
      18,
      4,
      4,
      4,
      11,
      0,
      2,
      3,
      3,
      7,
      13,
      8
    ],
    [
      0,
      9,
      16,
      14,
      5,
      3,
      1,
      9,
      11,
      3,
      3,
      9,
      18,
      3,
      4,
      12,
      7,
      4,
      13,
      3,
      2,
      1,
      2,
      12
    ],
    [
      18,
      4,
      19,
      15,
      8,
      14,
      10,
      19,
      6,
      8,
      3,
      10,
      18,
      18,
      9,
      18,
      18,
      18,
      7,
      7,
      0,
      3,
      18,
      15
    ],
    [
      1,
      2,
      9,
      2,
      2,
      2,
      17,
      11,
      2,
      0,
      6,
      18,
      14,
      0,
      9,
      10,
      7,
      7,
      17,
      8,
      14,
      16,
      16,
      16
    ],
    [
      9,
      9,
      0,
      10,
      12,
      8,
      11,
      1,
      1,
      10,
      6,
      16,
      2,
      19,
      8,
      6,
      13,
      8,
      13,
      16,
      18,
      9,
      4,
      10
    ],
    [
      13,
      6,
      0,
      19,
      10,
      13,
      3,
      13,
      5,
      3,
      17,
      14,
      19,
      5,
      13,
      15,
      2,
      2,
      3,
      19,
      7,
      15,
      12,
      4
    ]
  ]
}