{
  "timestamp": "2025-08-11T01:38:27.501Z",
  "date": "2025-08-11",
  "repositories": [
    {
      "org": "konveyor",
      "repo": "analyzer-lsp",
      "contributors": 19,
      "newContributors": 2,
      "avgIssueResponseMs": 99053444,
      "avgPRResponseMs": 38597153,
      "prMergeRate": 51,
      "openIssues": 35,
      "openPRs": 5
    },
    {
      "org": "konveyor",
      "repo": "enhancements",
      "contributors": 11,
      "newContributors": 2,
      "avgIssueResponseMs": 75396049,
      "avgPRResponseMs": 26463920,
      "prMergeRate": 51,
      "openIssues": 54,
      "openPRs": 16
    },
    {
      "org": "konveyor",
      "repo": "java-analyzer-bundle",
      "contributors": 11,
      "newContributors": 3,
      "avgIssueResponseMs": 98258944,
      "avgPRResponseMs": 40043766,
      "prMergeRate": 51,
      "openIssues": 33,
      "openPRs": 8
    },
    {
      "org": "konveyor",
      "repo": "kai",
      "contributors": 14,
      "newContributors": 3,
      "avgIssueResponseMs": 54070265,
      "avgPRResponseMs": 34077826,
      "prMergeRate": 51,
      "openIssues": 36,
      "openPRs": 6
    },
    {
      "org": "konveyor",
      "repo": "kantra",
      "contributors": 19,
      "newContributors": 5,
      "avgIssueResponseMs": 100439627,
      "avgPRResponseMs": 34043756,
      "prMergeRate": 51,
      "openIssues": 22,
      "openPRs": 15
    },
    {
      "org": "konveyor",
      "repo": "operator",
      "contributors": 19,
      "newContributors": 5,
      "avgIssueResponseMs": 26306199,
      "avgPRResponseMs": 49567663,
      "prMergeRate": 51,
      "openIssues": 48,
      "openPRs": 5
    },
    {
      "org": "konveyor",
      "repo": "rulesets",
      "contributors": 17,
      "newContributors": 5,
      "avgIssueResponseMs": 30240901,
      "avgPRResponseMs": 53353009,
      "prMergeRate": 51,
      "openIssues": 36,
      "openPRs": 6
    },
    {
      "org": "konveyor",
      "repo": "tackle2-hub",
      "contributors": 16,
      "newContributors": 3,
      "avgIssueResponseMs": 19498942,
      "avgPRResponseMs": 14138304,
      "prMergeRate": 51,
      "openIssues": 38,
      "openPRs": 15
    },
    {
      "org": "konveyor",
      "repo": "tackle2-ui",
      "contributors": 12,
      "newContributors": 3,
      "avgIssueResponseMs": 101478442,
      "avgPRResponseMs": 52155168,
      "prMergeRate": 51,
      "openIssues": 35,
      "openPRs": 11
    }
  ],
  "metrics": {
    "totalContributors": 138,
    "newContributors": 31,
    "avgResponseTime": 52621298.777777776,
    "avgIssueResponse": 67193645.8888889,
    "avgPRResponse": 38048951.666666664,
    "prMergeRate": 51,
    "openIssues": 337,
    "openPRs": 87,
    "repositories": 9
  },
  "prMetrics": {
    "avgReviewTime": 33772296,
    "avgMergeTime": 62447141,
    "avgRevisions": 1
  },
  "issueMetrics": {
    "closureRate": 52,
    "avgTimeToClose": 719601852,
    "avgTimeToFirstResponse": 13060697,
    "responseCoverage": 54,
    "communityResponseRate": 38
  },
  "maintainerMetrics": {
    "activeMaintainers": 10,
    "responseConcentration": 59
  },
  "activityHeatmap": [
    [
      3,
      3,
      5,
      5,
      3,
      3,
      4,
      3,
      4,
      9,
      5,
      8,
      5,
      7,
      9,
      5,
      8,
      6,
      7,
      7,
      6,
      4,
      6,
      4
    ],
    [
      6,
      6,
      7,
      6,
      6,
      7,
      8,
      9,
      10,
      16,
      19,
      15,
      16,
      18,
      19,
      19,
      15,
      19,
      8,
      10,
      11,
      12,
      12,
      5
    ],
    [
      5,
      7,
      3,
      3,
      4,
      6,
      10,
      11,
      11,
      16,
      15,
      18,
      19,
      18,
      18,
      19,
      19,
      17,
      10,
      9,
      11,
      10,
      10,
      6
    ],
    [
      7,
      7,
      6,
      6,
      4,
      7,
      9,
      8,
      11,
      17,
      17,
      19,
      15,
      18,
      15,
      19,
      15,
      15,
      10,
      9,
      11,
      11,
      12,
      4
    ],
    [
      6,
      5,
      3,
      6,
      6,
      3,
      9,
      11,
      11,
      15,
      18,
      17,
      15,
      17,
      19,
      17,
      19,
      18,
      11,
      11,
      12,
      11,
      10,
      3
    ],
    [
      6,
      5,
      3,
      3,
      6,
      4,
      9,
      9,
      12,
      19,
      16,
      19,
      15,
      18,
      15,
      19,
      16,
      18,
      11,
      8,
      12,
      11,
      8,
      6
    ],
    [
      4,
      2,
      5,
      2,
      1,
      4,
      4,
      5,
      7,
      7,
      9,
      6,
      7,
      5,
      7,
      5,
      6,
      8,
      5,
      4,
      4,
      7,
      6,
      2
    ]
  ]
}